mappdk/__init__.py
mappdk/abb.py
mappdk/fanuc.py
mappdk/kuka.py
mappdk/robotapp.py
mappdk-0.1.1.dist-info/LICENSE
mappdk-0.1.1.dist-info/METADATA
mappdk-0.1.1.dist-info/WHEEL
mappdk-0.1.1.dist-info/RECORD
