Metadata-Version: 2.1
Name: mappdk
Version: 0.1.1
Summary: Manufacturing Apps Development Kit
License: Apache-2.0 license
Author: Agajan Torayev
Author-email: torayeff@gmail.com
Requires-Python: >=3.6,<4.0
Classifier: License :: Other/Proprietary License
Classifier: Programming Language :: Python :: 3
Classifier: Programming Language :: Python :: 3.6
Classifier: Programming Language :: Python :: 3.7
Classifier: Programming Language :: Python :: 3.8
Classifier: Programming Language :: Python :: 3.9
Classifier: Programming Language :: Python :: 3.10
Classifier: Programming Language :: Python :: 3.11
